{
  "notes": [
    {
      "id": 22,
      "content": "test message",
      "userId": "877.8275555398556"
    },
    {
      "id": 2,
      "content": "cyndaquill is a pokemon",
      "userId": "872"
    },
    {
      "id": 4,
      "content": "today i read chapter 44something of kkkb",
      "userId": "877.8275555398556"
    },
    {
      "id": 5,
      "content": "the train",
      "userId": "878"
    },
    {
      "id": 66,
      "content": "romeo romeo donde estas que no te veo!",
      "userId": "871"
    }
  ]
}